treeboost_autograd/__init__.py
treeboost_autograd/booster_objectives.py
treeboost_autograd/pytorch_objective.py
treeboost_autograd-0.1.2.dist-info/LICENSE
treeboost_autograd-0.1.2.dist-info/WHEEL
treeboost_autograd-0.1.2.dist-info/METADATA
treeboost_autograd-0.1.2.dist-info/RECORD
