Metadata-Version: 2.1
Name: treeboost_autograd
Version: 0.1.2
Summary: treeboost_autograd
Home-page: https://github.com/TomerRonen34/treeboost_autograd
License: UNKNOWN
Author: Tomer Ronen
Author-email: tomer.ronen34@gmail.com
Classifier: License :: OSI Approved :: MIT License
Requires-Dist: numpy
Requires-Dist: torch
Requires-Dist: catboost ; extra == "dev"
Requires-Dist: xgboost ; extra == "dev"
Requires-Dist: lightgbm ; extra == "dev"
Requires-Dist: matplotlib ; extra == "dev"
Requires-Dist: pytest ; extra == "dev"
Requires-Dist: scikit_learn ; extra == "dev"
Provides-Extra: dev
